bigbert/__init__.py
bigbert/bigbert.py
bigbert/load_model.py
bigbert/util.py
bigbert/data/__init__.py
bigbert/data/frequency_dictionary_en_82_765.txt
bigbert/models/__init__.py
bigbert/models/bigbert.h5
bigbert/models/bigru.h5
bigbert-0.1.0.dist-info/LICENSE.txt
bigbert-0.1.0.dist-info/METADATA
bigbert-0.1.0.dist-info/WHEEL
bigbert-0.1.0.dist-info/top_level.txt
bigbert-0.1.0.dist-info/RECORD
