Metadata-Version: 2.1
Name: bigbert
Version: 0.1.0
Summary: A deep learning model for the automatic classification of online educational materials.
Home-page: https://github.com/BSU-CAST/BiGBERT
Author: Garrett Allen
Author-email: garrettallen@u.boisestate.edu
License: UNKNOWN
Project-URL: Bug Tracker, https://github.com/BSU-CAST/BiGBERT/issues
Platform: UNKNOWN
Classifier: Programming Language :: Python :: 3
Classifier: License :: OSI Approved :: MIT License
Classifier: Operating System :: OS Independent
Requires-Python: >=3.6
License-File: LICENSE.txt
Requires-Dist: flair (==0.6.1)
Requires-Dist: gdown
Requires-Dist: keras (==2.3.1)
Requires-Dist: keras-self-attention (==0.42.0)
Requires-Dist: numpy (==1.18.5)
Requires-Dist: pandas (==1.0.5)
Requires-Dist: pytorch-pretrained-bert (==0.6.2)
Requires-Dist: sklearn
Requires-Dist: symspellpy (==6.7.0)
Requires-Dist: tensorflow (==2.2.0)
Requires-Dist: torch (==1.7.0)
Requires-Dist: transformers (==3.5.1)
Requires-Dist: tqdm (==4.59.0)
